{"date_key":"2026-09-26","tibetan_year_name_en":"Fire Horse","image_key":"auspicious_days_fullmoon","gregorian":{"year":2026,"year_bo":"༢༠༢༦","month_en":"SEP","month_bo":"ཕྱི་ཟླ་དགུ་པ།","date":26,"date_bo":"༢༦","weekday_en":"Saturday","weekday_bo":"སྤེན་པ།"},"tibetan":{"year_en":"2153","year_bo":"༢༡༥༣","year_name_en":"Fire Horse","year_name_bo":"མེ་ཕོ་རྟ་ལོ།","month_en":"8","month_bo":"༨༽","month_name_en":"Thrum-Dawa","month_name_bo":"ཁྲུམས་ཟླ་བ།","animal_month_en":"Pig","animal_month_bo":"ཕག་ཟླ།","day_en":"15","day_bo":"༡༥","lunar_status_en":null,"lunar_status_bo":null},"significance":{"day_significance_en":"\"The Day of Amitabha Buddha\"","day_significance_bo":"སངས་རྒྱས་འོད་དཔག་མེད་ཉིན།","element_combo_en":"Earth-Earth","element_combo_bo":"ས་ས་།","meaning_of_coincidence_en":"Achievement: Fulfils wishes and brings blessings.","meaning_of_coincidence_bo":"གྲུབ་པ།"},"auspicious_day":{"name_en":"Full Moon","name_bo":"ཟླ་བ་ཉ་གང་། གསོ་སྦྱོང་།","short_description_en":"A powerful day for merit-making, purification, offerings, and strengthening positive intentions.","short_description_bo":"དགེ་རྩ་གསོག་པ་དང་། སྒྲིབ་པ་སྦྱོང་བ། མཆོད་པ་འབུལ་བ། དེ་བཞིན་བཟང་པོའི་འདུན་པ་བརྟན་པོ་བཟོ་བ་བཅས་ལ་ཤིན་ཏུ་ནུས་པ་ཆེ་བའི་ཉིན་མོ་ཞིག་ཡིན།"},"astrology_cards":[{"type":"naga_day","status_en":"extremely_auspicious_major","status_bo":"ཤིན་ཏུ་བཟང་།","image_key":"astrology_naga_days_major","popup_ref":"naga-major_popup_ref"},{"type":"flag_day","status_en":"auspicious","status_bo":"བཟང་།","image_key":"astrology_flag_days","popup_ref":"flag_popup_ref"},{"type":"fire_ritual","status_en":"avoid","status_bo":"ངན།","image_key":"astrology_fire_rituals","popup_ref":"fire_popup_ref"},{"type":"hair_cutting","status_en":"auspicious","status_bo":"བཟང་།","image_key":"astrology_hair_cutting","popup_ref":"hair_cutting_popup_ref"}],"torma_offering":{"direction_en":"southeast","image_key":"astrology_torma_offerings","popup_ref":"torma_popup_ref"},"empty_vase":{"direction_en":"south","image_key":"astrology_empty_vase","popup_ref":"empty_vase_popup_ref"},"daily_restriction":{"description_en":"avoid Family Gatherings","image_key":"astrology_daily_restrictions_kinship","popup_ref":"daily_restrictions_popup_ref"},"auspicious_times":{"description_en":"6:00 AM · 1:00 PM · 8:00 PM · 3:00 AM","image_key":"astrology_auspicious_time","popup_ref":"auspicious_time_popup_ref"},"events":[]}